{
    "1": "General ",
    "2": "First Times ",
    "3": "Combinations ",
    "4": "Glowing Experiences ",
    "5": "Difficult Experiences ",
    "6": "Bad Trips ",
    "7": "Train Wrecks & Trip Disasters ",
    "8": "Post Trip Problems ",
    "9": "Mystical Experiences ",
    "10": "Addiction & Habituation ",
    "11": "Retrospective / Summary ",
    "13": "Multi-Day Experience ",
    "14": "Sex Discussion ",
    "15": "Depression ",
    "16": "Alone ",
    "17": "Small Group (2-9) ",
    "18": "Rave / Dance Event ",
    "19": "Large Group (10+) ",
    "20": "Unknown Context ",
    "21": "Group Ceremony ",
    "22": "Music Discussion ",
    "23": "Nature / Outdoors ",
    "24": "Festival / Lg. Crowd ",
    "25": "Club / Bar ",
    "26": "What Was in That? ",
    "27": "Health Problems ",
    "28": "Various ",
    "29": "Overdose ",
    "30": "Preparation / Recipes ",
    "31": "Cultivation / Synthesis ",
    "32": "Health Benefits ",
    "33": "Pregnancy / Baby ",
    "34": "Loss of Magic ",
    "35": "School ",
    "36": "Hospital ",
    "37": "Entities / Beings ",
    "38": "Not Applicable ",
    "39": "Guides / Sitters ",
    "40": "HPPD / Lasting Visuals ",
    "41": "Families ",
    "42": "Second Hand Report ",
    "43": "Poetry ",
    "44": "Relationships ",
    "45": "Personal Preparation ",
    "46": "Hangover / Days After ",
    "47": "Medical Use ",
    "48": "Military ",
    "49": "Therapeutic Intent or Outcome ",
    "50": "Performance Enhancement ",
    "51": "Workplace ",
    "52": "Video ",
    "53": "Public Space (Museum, Park, etc) ",
    "54": "Large Party ",
    "55": "Therapeutic Session / Clinic "
}